{
    "cod": "200",
    "message": 0,
    "cnt": 5,
    "list": [
        {
            "dt": 1734912000,
            "main": {
                "temp": -5.85,
                "feels_like": -10.74,
                "temp_min": -5.85,
                "temp_max": -5.19,
                "pressure": 1033,
                "sea_level": 1033,
                "grnd_level": 1033,
                "humidity": 42,
                "temp_kf": -0.66
            },
            "weather": [
                {
                    "id": 800,
                    "main": "Clear",
                    "description": "clear sky",
                    "icon": "01n"
                }
            ],
            "clouds": {
                "all": 4
            },
            "wind": {
                "speed": 3.2,
                "deg": 350,
                "gust": 3.17
            },
            "visibility": 10000,
            "pop": 0,
            "sys": {
                "pod": "n"
            },
            "dt_txt": "2024-12-23 00:00:00"
        },
        {
            "dt": 1734922800,
            "main": {
                "temp": -6.25,
                "feels_like": -10.99,
                "temp_min": -6.28,
                "temp_max": -6.25,
                "pressure": 1035,
                "sea_level": 1035,
                "grnd_level": 1034,
                "humidity": 41,
                "temp_kf": 0.03
            },
            "weather": [
                {
                    "id": 800,
                    "main": "Clear",
                    "description": "clear sky",
                    "icon": "01n"
                }
            ],
            "clouds": {
                "all": 2
            },
            "wind": {
                "speed": 2.98,
                "deg": 25,
                "gust": 2.98
            },
            "visibility": 10000,
            "pop": 0,
            "sys": {
                "pod": "n"
            },
            "dt_txt": "2024-12-23 03:00:00"
        },
        {
            "dt": 1734933600,
            "main": {
                "temp": -6.62,
                "feels_like": -11.53,
                "temp_min": -6.62,
                "temp_max": -6.62,
                "pressure": 1036,
                "sea_level": 1036,
                "grnd_level": 1034,
                "humidity": 40,
                "temp_kf": 0
            },
            "weather": [
                {
                    "id": 800,
                    "main": "Clear",
                    "description": "clear sky",
                    "icon": "01n"
                }
            ],
            "clouds": {
                "all": 1
            },
            "wind": {
                "speed": 3.07,
                "deg": 16,
                "gust": 3.39
            },
            "visibility": 10000,
            "pop": 0,
            "sys": {
                "pod": "n"
            },
            "dt_txt": "2024-12-23 06:00:00"
        },
        {
            "dt": 1734944400,
            "main": {
                "temp": -6.96,
                "feels_like": -11.75,
                "temp_min": -6.96,
                "temp_max": -6.96,
                "pressure": 1037,
                "sea_level": 1037,
                "grnd_level": 1035,
                "humidity": 43,
                "temp_kf": 0
            },
            "weather": [
                {
                    "id": 800,
                    "main": "Clear",
                    "description": "clear sky",
                    "icon": "01n"
                }
            ],
            "clouds": {
                "all": 0
            },
            "wind": {
                "speed": 2.9,
                "deg": 21,
                "gust": 3.28
            },
            "visibility": 10000,
            "pop": 0,
            "sys": {
                "pod": "n"
            },
            "dt_txt": "2024-12-23 09:00:00"
        },
        {
            "dt": 1734955200,
            "main": {
                "temp": -6.95,
                "feels_like": -9.78,
                "temp_min": -6.95,
                "temp_max": -6.95,
                "pressure": 1037,
                "sea_level": 1037,
                "grnd_level": 1036,
                "humidity": 43,
                "temp_kf": 0
            },
            "weather": [
                {
                    "id": 800,
                    "main": "Clear",
                    "description": "clear sky",
                    "icon": "01n"
                }
            ],
            "clouds": {
                "all": 3
            },
            "wind": {
                "speed": 1.55,
                "deg": 32,
                "gust": 1.47
            },
            "visibility": 10000,
            "pop": 0,
            "sys": {
                "pod": "n"
            },
            "dt_txt": "2024-12-23 12:00:00"
        }
    ],
    "city": {
        "id": 5128581,
        "name": "New York",
        "coord": {
            "lat": 40.7143,
            "lon": -74.006
        },
        "country": "US",
        "population": 8175133,
        "timezone": -18000,
        "sunrise": 1734869839,
        "sunset": 1734903140
    }
}